gwpconfig/__init__.py
gwpconfig/commconstants.py
gwpconfig/wall.py
gwpconfig-1.0.1.dist-info/LICENSE
gwpconfig-1.0.1.dist-info/METADATA
gwpconfig-1.0.1.dist-info/WHEEL
gwpconfig-1.0.1.dist-info/top_level.txt
gwpconfig-1.0.1.dist-info/RECORD
